[
	{
		"name": "bug",
		"color": "#A8B820",
		"halfEffectiveAgainst": ["fairy", "fighting", "fire", "flying", "ghost", "poison", "steel"],
		"twiceEffectiveAgainst": ["dark", "grass", "psychic"],
		"zeroEffectiveAgainst": []
	},
	{
		"name": "dark",
		"color": "#705848",
		"halfEffectiveAgainst": ["dark", "fairy", "fighting"],
		"twiceEffectiveAgainst": ["ghost", "psychic"],
		"zeroEffectiveAgainst": []
	},
	{
		"name": "dragon",
		"color": "#7038F8",
		"halfEffectiveAgainst": ["steel"],
		"twiceEffectiveAgainst": ["dragon"],
		"zeroEffectiveAgainst": ["fairy"]
	},
	{
		"name": "electric",
		"color": "#F8D030",
		"halfEffectiveAgainst": ["dragon", "electric", "grass"],
		"twiceEffectiveAgainst": ["flying", "water"],
		"zeroEffectiveAgainst": []
	},
	{
		"name": "fairy",
		"color": "#EE99AC",
		"halfEffectiveAgainst": ["fire", "poison", "steel"],
		"twiceEffectiveAgainst": ["dark", "dragon", "fighting"],
		"zeroEffectiveAgainst": []
	},
	{
		"name": "fighting",
		"color": "#C03028",
		"halfEffectiveAgainst": ["bug", "fairy", "flying", "poison", "psychic"],
		"twiceEffectiveAgainst": ["dark", "ice", "normal", "rock", "steel"],
		"zeroEffectiveAgainst": ["ghost"]
	},
	{
		"name": "fire",
		"color": "#F08030",
		"halfEffectiveAgainst": ["dragon", "fire", "rock", "water"],
		"twiceEffectiveAgainst": ["bug", "grass", "ice", "steel"],
		"zeroEffectiveAgainst": []
	},
	{
		"name": "flying",
		"color": "#A890F0",
		"halfEffectiveAgainst": ["electric", "rock", "steel"],
		"twiceEffectiveAgainst": ["bug", "fighting", "grass"],
		"zeroEffectiveAgainst": []
	},
	{
		"name": "ghost",
		"color": "#705898",
		"halfEffectiveAgainst": ["dark"],
		"twiceEffectiveAgainst": ["ghost", "psychic"],
		"zeroEffectiveAgainst": ["normal"]
	},
	{
		"name": "grass",
		"color": "#78C850",
		"halfEffectiveAgainst": ["bug", "dragon", "fire", "flying", "grass", "poison"],
		"twiceEffectiveAgainst": ["ground", "rock", "water"],
		"zeroEffectiveAgainst": []
	},
	{
		"name": "ground",
		"color": "#E0C068",
		"halfEffectiveAgainst": ["bug", "grass"],
		"twiceEffectiveAgainst": ["electric", "fire", "poison", "rock", "steel"],
		"zeroEffectiveAgainst": ["flying"]
	},
	{
		"name": "ice",
		"color": "#98D8D8",
		"halfEffectiveAgainst": ["fire", "ice", "steel", "water"],
		"twiceEffectiveAgainst": ["dragon", "flying", "grass", "ground"],
		"zeroEffectiveAgainst": []
	},
	{
		"name": "normal",
		"color": "#A8A878",
		"halfEffectiveAgainst": [],
		"twiceEffectiveAgainst": [],
		"zeroEffectiveAgainst": []
	},
	{
		"name": "poison",
		"color": "#A040A0",
		"halfEffectiveAgainst": ["ghost", "ground", "poison", "rock"],
		"twiceEffectiveAgainst": ["fairy", "grass"],
		"zeroEffectiveAgainst": ["steel"]
	},
	{
		"name": "psychic",
		"color": "#F85888",
		"halfEffectiveAgainst": ["psychic"],
		"twiceEffectiveAgainst": ["fighting", "poison"],
		"zeroEffectiveAgainst": ["dark"]
	},
	{
		"name": "rock",
		"color": "#B8A038",
		"halfEffectiveAgainst": ["fighting", "ground", "steel"],
		"twiceEffectiveAgainst": ["bug", "fire", "flying", "ice"],
		"zeroEffectiveAgainst": []
	},
	{
		"name": "steel",
		"color": "#B8B8D0",
		"halfEffectiveAgainst": ["electric", "fire", "steel", "water"],
		"twiceEffectiveAgainst": ["fairy", "ice", "rock"],
		"zeroEffectiveAgainst": []
	},
	{
		"name": "water",
		"color": "#6890F0",
		"halfEffectiveAgainst": ["dragon", "grass", "water"],
		"twiceEffectiveAgainst": ["fire", "ground", "rock"],
		"zeroEffectiveAgainst": []
	}
]
